{
    "version": 5,
    "cmakeMinimumRequired": { "major": 3, "minor": 24 },
    "configurePresets": [
      {
        "name": "windows-debug",
        "displayName": "Windows (MinGW + Ninja) - Debug",
        "generator": "Ninja",
        "binaryDir": "${sourceDir}/build/debug",
        "cacheVariables": {
          "CMAKE_BUILD_TYPE": "Debug",
          "CMAKE_EXPORT_COMPILE_COMMANDS": "ON"
        }
      },
      {
        "name": "windows-release",
        "displayName": "Windows (MinGW + Ninja) - Release",
        "generator": "Ninja",
        "binaryDir": "${sourceDir}/build/release",
        "cacheVariables": {
          "CMAKE_BUILD_TYPE": "Release",
          "CMAKE_EXPORT_COMPILE_COMMANDS": "ON"
        }
      }
    ],
    "buildPresets": [
      {
        "name": "debug",
        "configurePreset": "windows-debug"
      },
      {
        "name": "release",
        "configurePreset": "windows-release"
      }
    ]
  }
  